odoo/addons/stock_picking_force_availability/README.rst
odoo/addons/stock_picking_force_availability/__init__.py
odoo/addons/stock_picking_force_availability/__manifest__.py
odoo/addons/stock_picking_force_availability/i18n/ca_ES.po
odoo/addons/stock_picking_force_availability/i18n/es.po
odoo/addons/stock_picking_force_availability/models/__init__.py
odoo/addons/stock_picking_force_availability/models/stock_picking.py
odoo/addons/stock_picking_force_availability/static/description/icon.png
odoo/addons/stock_picking_force_availability/views/stock_picking_views.xml
odoo_addon_stock_picking_force_availability-15.0.1.0.1.2.dist-info/METADATA
odoo_addon_stock_picking_force_availability-15.0.1.0.1.2.dist-info/WHEEL
odoo_addon_stock_picking_force_availability-15.0.1.0.1.2.dist-info/top_level.txt
odoo_addon_stock_picking_force_availability-15.0.1.0.1.2.dist-info/RECORD
